extractreqs/__init__.py
extractreqs/__main__.py
extractreqs/cli.py
extractreqs/extractreqs.py
extractreqs-0.1.1.dist-info/licenses/LICENSE
extractreqs-0.1.1.dist-info/METADATA
extractreqs-0.1.1.dist-info/WHEEL
extractreqs-0.1.1.dist-info/entry_points.txt
extractreqs-0.1.1.dist-info/top_level.txt
extractreqs-0.1.1.dist-info/RECORD
