Metadata-Version: 2.4
Name: extractreqs
Version: 0.1.1
Summary: A tool to automatically extract and generate requirements.txt from Python source code by analyzing imports.
Author: hasanaliozkan
Author-email: hasanaliozkan <hasanaliozkan@mu.edu.tr>
Maintainer-email: hasanaliozkan <hasanaliozkan@mu.edu.tr>
License: MIT
Project-URL: bugs, https://github.com/hasanaliozkan-dev/extractreqs/issues
Project-URL: changelog, https://github.com/hasanaliozkan-dev/extractreqs/blob/master/changelog.md
Project-URL: homepage, https://github.com/hasanaliozkan-dev/extractreqs
Requires-Python: >=3.9
License-File: LICENSE
Requires-Dist: typer
Provides-Extra: test
Requires-Dist: coverage; extra == "test"
Requires-Dist: pytest; extra == "test"
Requires-Dist: ruff; extra == "test"
Requires-Dist: ty; extra == "test"
Requires-Dist: ipdb; extra == "test"
Dynamic: author
Dynamic: license-file
